{ "dataTitle": "orderCode", "formField": [ { "type": "card", "label": "工单信息", "fields": [{ "type": "input", "title": "标题", "value": "label" }], "fieldId": "orderinfoCard", "noListed": true, "fieldType": 0 }, { "icon": "column", "name": "三列布局", "type": "multiColumn", "label": "三列布局", "fields": [{ "type": "input", "title": "标题", "value": "label" }], "columns": 3, "fieldId": "orderinfo", "children": [ { "type": "input", "label": "工单编码", "fields": [{ "type": "input", "title": "标题", "value": "label" }], "fieldId": "orderCode", "codeType": "order", "disabled": false, "fieldType": 0, "placeholder": "系统生成", "hideCondition": "EditDetail" }, { "type": "radio", "label": "需求来源", "fields": [{ "type": "input", "title": "标题", "value": "label" }], "fieldId": "demandSource", "options": [ { "itemName": "面向库存", "itemValue": "0" }, { "itemName": "面向销售订单", "itemValue": "1" } ], "disabled": true, "required": true, "fieldType": 0 }, { "type": "relation", "label": "客户信息", "table": "custom_form_contactcompany", "fields": [{ "type": "input", "title": "标题", "value": "label" }], "fieldId": "customId", "fieldType": 0, "disabledSort": true, "hideCondition": "onlyList" }, { "type": "relation", "label": "产品信息", "table": "custom_form_inventoryfile", "fields": [{ "type": "input", "title": "标题", "value": "label" }], "fieldId": "materialId", "disabled": true, "required": true, "eventname": "order_inventoryfile", "fieldType": 0, "paramsFields": "materialId" }, { "type": "order-process-detail", "label": "选择工艺", "fields": [{ "type": "input", "title": "标题", "value": "label" }], "fieldId": "orderprocess", "disabled": true, "noListed": true, "fieldType": 0, "hideCondition": "isDetail" }, { "type": "relation", "label": "关联销售订单", "table": "custom_form_saleorder", "fields": [{ "type": "input", "title": "标题", "value": "label" }], "params": { "status": "0" }, "fieldId": "salesId", "disabled": true, "required": true, "fieldType": 0, "hideCondition": "onlyList" }, { "type": "relation", "label": "关联销售订单", "table": "custom_form_saleOrderSelect", "fields": [{ "type": "input", "title": "标题", "value": "label" }], "params": { "status": "0" }, "fieldId": "salesOrderId", "disabled": true, "noListed": true, "required": true, "eventname": "order_saleorderdetail", "fieldType": 0, "hideCondition": "{\"relation\":\"==\",\"field\":\"demandSource\",\"dvalue\":\"1\"}" }, { "type": "input", "label": "产品规格", "fields": [{ "type": "input", "title": "标题", "value": "label" }], "fieldId": "specs", "fieldType": 0, "hideCondition": "isDetail" }, { "type": "relation", "label": "工艺路线", "table": "custom_form_routemain", "fields": [{ "type": "input", "title": "标题", "value": "label" }], "fieldId": "routeId", "noListed": true, "required": true, "eventname": "order_routemain", "fieldType": 0, "paramsFields": "routeId" }, { "type": "date", "label": "订单交付时间", "fields": [{ "type": "input", "title": "标题", "value": "label" }], "fieldId": "orderDeliveryTime", "dateType": "yyyy-MM-dd HH:mm:ss", "disabled": true, "fieldType": 0, "placeholder": "", "hideCondition": "{\"relation\":\"==\",\"field\":\"demandSource\",\"dvalue\":\"1\"}" }, { "type": "datetime", "label": "要求完成时间", "fields": [{ "type": "input", "title": "标题", "value": "label" }], "fieldId": "needTime", "dateType": "yyyy-MM-dd HH:mm:ss", "disabled": true, "required": true, "fieldType": 0, "placeholder": "" }, { "type": "inventory", "label": "工单数量", "fields": [{ "type": "input", "title": "标题", "value": "label" }], "regexp": "positiveInteger", "fieldId": "needCount", "disabled": true, "required": true, "fieldType": 0, "inputType": "number", "placeholder": "" }, { "type": "subUnits", "label": "辅计量", "fields": [{ "type": "input", "title": "标题", "value": "label" }], "regexp": "positiveInteger", "fieldId": "subUnits", "required": true, "fieldType": 0, "inputType": "number", "hideCondition": "onlyList" }, { "type": "date", "label": "最早开工时间", "fields": [{ "type": "input", "title": "标题", "value": "label" }], "fieldId": "earliestStartTime", "dateType": "yyyy-MM-dd HH:mm", "disabled": true, "fieldType": 0, "placeholder": "" }, { "type": "datetime-nosecond", "label": "计划开始时间", "fields": [{ "type": "input", "title": "标题", "value": "label" }], "fieldId": "orderTimeStart", "dateType": "yyyy-MM-dd HH:mm:ss", "fieldType": 0, "hideCondition": "listDetail" }, { "type": "date-danger", "label": "计划结束时间", "fields": [{ "type": "input", "title": "标题", "value": "label" }], "fieldId": "orderTimeEnd", "dateType": "yyyy-MM-dd HH:mm:ss", "fieldType": 0, "hideCondition": "listDetail" }, { "tip": "（系统字段-所属部门）", "type": "tree", "label": "所属部门", "table": "department", "fields": [{ "type": "input", "title": "标题", "value": "label" }], "fieldId": "depId", "disabled": true, "fieldName": "department", "fieldType": 0, "placeholder": "请选择所属部门" }, { "type": "relation", "label": "派发人员", "table": "custom_form_user", "fields": [{ "type": "input", "title": "标题", "value": "label" }], "fieldId": "distributorId", "eventname": "order_distribute", "fieldType": 0, "hideCondition": "listDetail" }, { "type": "datetime", "label": "派发时间", "fields": [{ "type": "input", "title": "标题", "value": "label" }], "fieldId": "dispatchTime", "dateType": "yyyy-MM-dd HH:mm:ss", "fieldType": 0, "hideCondition": "listDetail" }, { "type": "select", "label": "工单状态", "fields": [{ "type": "input", "title": "标题", "value": "label" }], "fieldId": "status", "options": [ { "itemName": "未开始   ", "itemValue": "5" }, { "itemName": "执行中", "itemValue": "1" }, { "itemName": "已完成", "itemValue": "2" }, { "itemName": "已撤回", "itemValue": "6" }, { "itemName": "已关闭", "itemValue": "3" } ], "required": true, "fieldType": 0, "defaultValue": "0", "disabledSort": true, "hideCondition": "onlyList" }, { "type": "relation", "label": "计划人员", "table": "custom_form_user", "fields": [{ "type": "input", "title": "标题", "value": "label" }], "fieldId": "planningPersonnelId", "disabled": true, "eventname": "order_user", "fieldType": 0 }, { "type": "input-prefix", "label": "已派发数量", "fields": [{ "type": "input", "title": "标题", "value": "label" }], "fieldId": "sentCount", "fieldType": 0, "hideCondition": "onlyList" }, { "type": "input-prefix", "label": "未派发数量", "fields": [{ "type": "input", "title": "标题", "value": "label" }], "fieldId": "planDispatch", "fieldType": 0, "disabledSort": true, "hideCondition": "onlyList" }, { "type": "input-prefix", "label": "已完工数量", "fields": [{ "type": "input", "title": "标题", "value": "label" }], "fieldId": "completedCount", "fieldType": 0, "hideCondition": "listDetail" }, { "type": "input", "label": "生产进度", "fields": [{ "type": "input", "title": "标题", "value": "label" }], "fieldId": "completeSchedule", "fieldType": 0, "disabledSort": true, "hideCondition": "listDetail" }, { "type": "input", "label": "完成比例", "fields": [{ "type": "input", "title": "标题", "value": "label" }], "fieldId": "completionRatio", "fieldType": 0, "disabledSort": true, "hideCondition": "onlyList" }, { "type": "select", "label": "备料状态", "fields": [{ "type": "input", "title": "标题", "value": "label" }], "fieldId": "issueControlStatus", "options": [ { "itemName": "未开始   ", "itemValue": "0" }, { "itemName": "执行中", "itemValue": "3" }, { "itemName": "已完成", "itemValue": "4" }, { "itemName": "已关闭", "itemValue": "5" } ], "fieldType": 0, "hideCondition": "onlyList" }, { "type": "select", "label": "齐套状态", "fields": [{ "type": "input", "title": "标题", "value": "label" }], "fieldId": "allSetStatus", "options": [ { "itemName": "齐套", "itemValue": "1" }, { "itemName": "缺料", "itemValue": "2" }, { "itemName": "缺料但有替代物", "itemValue": "3" } ], "fieldType": 0, "disabledSort": true, "hideCondition": "onlyList" } ], "noListed": true, "fieldType": 0 }, { "type": "sub-work-order", "label": "批量创建子工单", "fields": [{ "type": "input", "title": "标题", "value": "label" }], "fieldId": "subOrderListShow", "children": [ { "type": "input", "label": "BOM层级", "width": 100, "fieldId": "level", "noListed": true }, { "type": "relation", "label": "物料信息", "table": "custom_form_inventoryfile", "fieldId": "materialId", "noListed": true, "required": true, "eventname": "order_inventoryfile" }, { "type": "relation", "label": "工艺路线", "table": "custom_form_routemain", "fieldId": "routeId", "noListed": true, "required": true, "eventname": "order_routemain", "outParams": "subRouteId" }, { "type": "input-prefix", "label": "工单数量", "width": 160, "regexp": "positiveInteger", "fieldId": "needCount", "disabled": true, "noListed": true, "required": true, "validate": "", "inputType": "number" }, { "type": "date", "label": "要求完成时间", "width": 200, "format": "yyyy-MM-dd HH:mm:ss", "fieldId": "needTime", "disabled": true, "noListed": true, "required": true, "validate": "{\"required\":true}" }, { "type": "relation", "label": "计划人员", "table": "custom_form_user", "fieldId": "planningPersonnelId", "disabled": true, "noListed": true, "eventname": "order_user", "fieldType": 0 } ], "noListed": true }, { "type": "card", "label": "BOM设置", "fields": [{ "type": "input", "title": "标题", "value": "label" }], "fieldId": "bomSetting", "noListed": true, "fieldType": 0 }, { "type": "materiel-bom", "label": "BOM清单", "fields": [{ "type": "input", "title": "标题", "value": "label" }], "fieldId": "bomData", "noListed": true }, { "type": "card", "label": "工序设置", "fields": [{ "type": "input", "title": "标题", "value": "label" }], "fieldId": "routeDataCard", "noListed": true, "fieldType": 0 }, { "type": "procedure", "label": "", "fields": [{ "type": "input", "title": "标题", "value": "label" }], "fieldId": "routeDeta", "noListed": true, "fieldType": 0 } ], "printType": "1", "showFields": "orderCode,materialId,status,needCount,subUnits,depId,planningPersonnelId,needTime,distributorId,dispatchTime,orderTimeStart,orderTimeEnd,demandSource,salesId,customId,orderDeliveryTime,issueControlStatus", "queryCriteria": "orderCode,materialId,status,depId,planningPersonnelId,needTime,distributorId,dispatchTime,orderTimeStart,orderTimeEnd,demandSource,salesId,customId,orderDeliveryTime,issueControlStatus" }